{
  "project_info": {
    "project_number": "71078655313",
    "firebase_url": "https://house-of-avatars-5d094-default-rtdb.firebaseio.com",
    "project_id": "house-of-avatars-5d094",
    "storage_bucket": "house-of-avatars-5d094.appspot.com"
  },
  "client": [
    {
      "client_info": {
        "mobilesdk_app_id": "1:71078655313:android:eb3d78bbe4698139b6cf70",
        "android_client_info": {
          "package_name": "com.houseofavatars"
        }
      },
      "oauth_client": [],
      "api_key": [
        {
          "current_key": "AIzaSyAOwm6uJJV-O24-jHvNeJ84YImQ9AVereE"
        }
      ],
      "services": {
        "appinvite_service": {
          "other_platform_oauth_client": []
        }
      }
    }
  ],
  "configuration_version": "1"
}